{
  "date": "2025-07-02",
  "projects": {
    "Cursor": {
      "totalLinesAdded": 311,
      "totalLinesRemoved": 27,
      "totalActiveTime": 9,
      "files": {
        "c:\\Cursor\\Alpha\\login_animado_gradiente.py": [
          {
            "timestamp": "2025-07-02T06:38:03.675Z",
            "fileName": "c:\\Cursor\\Alpha\\login_animado_gradiente.py",
            "fileType": ".py",
            "linesAdded": 1,
            "linesRemoved": 0,
            "projectName": "Cursor",
            "content": {
              "added": [],
              "removed": []
            },
            "duration": 0,
            "language": "py"
          },
          {
            "timestamp": "2025-07-02T06:38:04.753Z",
            "fileName": "c:\\Cursor\\Alpha\\login_animado_gradiente.py",
            "fileType": ".py",
            "linesAdded": 56,
            "linesRemoved": 0,
            "projectName": "Cursor",
            "content": {
              "added": [],
              "removed": []
            },
            "duration": 1,
            "language": "py"
          },
          {
            "timestamp": "2025-07-02T06:38:29.496Z",
            "fileName": "c:\\Cursor\\Alpha\\login_animado_gradiente.py",
            "fileType": ".py",
            "linesAdded": 6,
            "linesRemoved": 0,
            "projectName": "Cursor",
            "content": {
              "added": [],
              "removed": []
            },
            "duration": 1,
            "language": "py"
          },
          {
            "timestamp": "2025-07-02T06:38:50.779Z",
            "fileName": "c:\\Cursor\\Alpha\\login_animado_gradiente.py",
            "fileType": ".py",
            "linesAdded": 3,
            "linesRemoved": 0,
            "projectName": "Cursor",
            "content": {
              "added": [],
              "removed": []
            },
            "duration": 1,
            "language": "py"
          }
        ],
        "c:\\Cursor\\Alpha\\login_animado_linhas.py": [
          {
            "timestamp": "2025-07-02T06:39:15.038Z",
            "fileName": "c:\\Cursor\\Alpha\\login_animado_linhas.py",
            "fileType": ".py",
            "linesAdded": 1,
            "linesRemoved": 0,
            "projectName": "Cursor",
            "content": {
              "added": [],
              "removed": []
            },
            "duration": 1,
            "language": "py"
          },
          {
            "timestamp": "2025-07-02T06:39:15.888Z",
            "fileName": "c:\\Cursor\\Alpha\\login_animado_linhas.py",
            "fileType": ".py",
            "linesAdded": 63,
            "linesRemoved": 0,
            "projectName": "Cursor",
            "content": {
              "added": [],
              "removed": []
            },
            "duration": 1,
            "language": "py"
          },
          {
            "timestamp": "2025-07-02T06:45:36.767Z",
            "fileName": "c:\\Cursor\\Alpha\\login_animado_linhas.py",
            "fileType": ".py",
            "linesAdded": 9,
            "linesRemoved": 0,
            "projectName": "Cursor",
            "content": {
              "added": [],
              "removed": []
            },
            "duration": 0,
            "language": "py"
          }
        ],
        "c:\\Cursor\\Alpha\\login_moderno.py": [
          {
            "timestamp": "2025-07-02T07:21:05.687Z",
            "fileName": "c:\\Cursor\\Alpha\\login_moderno.py",
            "fileType": ".py",
            "linesAdded": 1,
            "linesRemoved": 0,
            "projectName": "Cursor",
            "content": {
              "added": [],
              "removed": []
            },
            "duration": 0,
            "language": "py"
          },
          {
            "timestamp": "2025-07-02T07:21:06.645Z",
            "fileName": "c:\\Cursor\\Alpha\\login_moderno.py",
            "fileType": ".py",
            "linesAdded": 113,
            "linesRemoved": 0,
            "projectName": "Cursor",
            "content": {
              "added": [],
              "removed": []
            },
            "duration": 1,
            "language": "py"
          },
          {
            "timestamp": "2025-07-02T07:21:41.824Z",
            "fileName": "c:\\Cursor\\Alpha\\login_moderno.py",
            "fileType": ".py",
            "linesAdded": 13,
            "linesRemoved": 0,
            "projectName": "Cursor",
            "content": {
              "added": [],
              "removed": []
            },
            "duration": 1,
            "language": "py"
          },
          {
            "timestamp": "2025-07-02T07:37:02.048Z",
            "fileName": "c:\\Cursor\\Alpha\\login_moderno.py",
            "fileType": ".py",
            "linesAdded": 28,
            "linesRemoved": 0,
            "projectName": "Cursor",
            "content": {
              "added": [],
              "removed": []
            },
            "duration": 0,
            "language": "py"
          },
          {
            "timestamp": "2025-07-02T07:38:51.628Z",
            "fileName": "c:\\Cursor\\Alpha\\login_moderno.py",
            "fileType": ".py",
            "linesAdded": 6,
            "linesRemoved": 0,
            "projectName": "Cursor",
            "content": {
              "added": [],
              "removed": []
            },
            "duration": 2,
            "language": "py"
          },
          {
            "timestamp": "2025-07-02T07:51:41.766Z",
            "fileName": "c:\\Cursor\\Alpha\\login_moderno.py",
            "fileType": ".py",
            "linesAdded": 11,
            "linesRemoved": 0,
            "projectName": "Cursor",
            "content": {
              "added": [],
              "removed": []
            },
            "duration": 0,
            "language": "py"
          },
          {
            "timestamp": "2025-07-02T08:50:34.157Z",
            "fileName": "c:\\Cursor\\Alpha\\login_moderno.py",
            "fileType": ".py",
            "linesAdded": 0,
            "linesRemoved": 27,
            "projectName": "Cursor",
            "content": {
              "added": [],
              "removed": []
            },
            "duration": 0,
            "language": "py"
          }
        ]
      },
      "languageStats": {
        "py": 3
      },
      "changeFrequency": {
        "3": 3
      },
      "topFiles": [
        "c:\\Cursor\\Alpha\\login_animado_gradiente.py"
      ],
      "averageChangeSize": 16.5
    }
  },
  "totalActiveTime": 3,
  "totalProjects": 1,
  "totalFiles": 1,
  "mostActiveHours": [
    3
  ],
  "mostUsedLanguages": [
    "py"
  ]
}